writepy/__init__.py
writepy/code.py
writepy/dummy.py
writepy/matcher.py
writepy/meta.py
writepy-0.1.dist-info/LICENSE
writepy-0.1.dist-info/METADATA
writepy-0.1.dist-info/WHEEL
writepy-0.1.dist-info/entry_points.txt
writepy-0.1.dist-info/top_level.txt
writepy-0.1.dist-info/RECORD
