Metadata-Version: 2.1
Name: writepy
Version: 0.1
Summary: ultimate type-safe code generation for python, only for being productive
Home-page: https://github.com/thautawarm/writepy
Author: thautawarm
Author-email: twshere@outlook.com
License: mit
Keywords: metaprogramming,code generation
Platform: any
Classifier: Programming Language :: Python :: 3.5
Classifier: Programming Language :: Python :: 3.6
Classifier: Programming Language :: Python :: 3.7
Classifier: Programming Language :: Python :: 3.8
Classifier: Programming Language :: Python :: Implementation :: CPython
Requires-Python: >=3.5.0
Requires-Dist: ast-compat (>=0.10.0)
